<?xml version="1.0" encoding="utf-8" standalone="yes"?>
<CURRENCIES>
  <LAST_UPDATE>2020-07-31</LAST_UPDATE>
  <CURRENCY>
    <NAME>Dollar</NAME>
    <UNIT>1</UNIT>
    <CURRENCYCODE>USD</CURRENCYCODE>
    <COUNTRY>USA</COUNTRY>
    <RATE>3.408</RATE>
    <CHANGE>-0.029</CHANGE>
  </CURRENCY>
  <CURRENCY>
    <NAME>Pound</NAME>
    <UNIT>1</UNIT>
    <CURRENCYCODE>GBP</CURRENCYCODE>
    <COUNTRY>Great Britain</COUNTRY>
    <RATE>4.4720</RATE>
    <CHANGE>1.124</CHANGE>
  </CURRENCY>
  <CURRENCY>
    <NAME>Yen</NAME>
    <UNIT>100</UNIT>
    <CURRENCYCODE>JPY</CURRENCYCODE>
    <COUNTRY>Japan</COUNTRY>
    <RATE>3.2542</RATE>
    <CHANGE>0.179</CHANGE>
  </CURRENCY>
  <CURRENCY>
    <NAME>Euro</NAME>
    <UNIT>1</UNIT>
    <CURRENCYCODE>EUR</CURRENCYCODE>
    <COUNTRY>EMU</COUNTRY>
    <RATE>4.0388</RATE>
    <CHANGE>0.973</CHANGE>
  </CURRENCY>
  <CURRENCY>
    <NAME>Dollar</NAME>
    <UNIT>1</UNIT>
    <CURRENCYCODE>AUD</CURRENCYCODE>
    <COUNTRY>Australia</COUNTRY>
    <RATE>2.4504</RATE>
    <CHANGE>0.172</CHANGE>
  </CURRENCY>
  <CURRENCY>
    <NAME>Dollar</NAME>
    <UNIT>1</UNIT>
    <CURRENCYCODE>CAD</CURRENCYCODE>
    <COUNTRY>Canada</COUNTRY>
    <RATE>2.5384</RATE>
    <CHANGE>-0.51</CHANGE>
  </CURRENCY>
  <CURRENCY>
    <NAME>krone</NAME>
    <UNIT>1</UNIT>
    <CURRENCYCODE>DKK</CURRENCYCODE>
    <COUNTRY>Denmark</COUNTRY>
    <RATE>0.5425</RATE>
    <CHANGE>0.949</CHANGE>
  </CURRENCY>
  <CURRENCY>
    <NAME>Krone</NAME>
    <UNIT>1</UNIT>
    <CURRENCYCODE>NOK</CURRENCYCODE>
    <COUNTRY>Norway</COUNTRY>
    <RATE>0.3759</RATE>
    <CHANGE>0.08</CHANGE>
  </CURRENCY>
  <CURRENCY>
    <NAME>Rand</NAME>
    <UNIT>1</UNIT>
    <CURRENCYCODE>ZAR</CURRENCYCODE>
    <COUNTRY>South Africa</COUNTRY>
    <RATE>0.2012</RATE>
    <CHANGE>-2.755</CHANGE>
  </CURRENCY>
  <CURRENCY>
    <NAME>Krona</NAME>
    <UNIT>1</UNIT>
    <CURRENCYCODE>SEK</CURRENCYCODE>
    <COUNTRY>Sweden</COUNTRY>
    <RATE>0.3924</RATE>
    <CHANGE>0.952</CHANGE>
  </CURRENCY>
  <CURRENCY>
    <NAME>Franc</NAME>
    <UNIT>1</UNIT>
    <CURRENCYCODE>CHF</CURRENCYCODE>
    <COUNTRY>Switzerland</COUNTRY>
    <RATE>3.7537</RATE>
    <CHANGE>1.025</CHANGE>
  </CURRENCY>
  <CURRENCY>
    <NAME>Dinar</NAME>
    <UNIT>1</UNIT>
    <CURRENCYCODE>JOD</CURRENCYCODE>
    <COUNTRY>Jordan</COUNTRY>
    <RATE>4.8068</RATE>
    <CHANGE>-0.04</CHANGE>
  </CURRENCY>
  <CURRENCY>
    <NAME>Pound</NAME>
    <UNIT>10</UNIT>
    <CURRENCYCODE>LBP</CURRENCYCODE>
    <COUNTRY>Lebanon</COUNTRY>
    <RATE>0.0225</RATE>
    <CHANGE>0</CHANGE>
  </CURRENCY>
  <CURRENCY>
    <NAME>Pound</NAME>
    <UNIT>1</UNIT>
    <CURRENCYCODE>EGP</CURRENCYCODE>
    <COUNTRY>Egypt</COUNTRY>
    <RATE>0.2134</RATE>
    <CHANGE>-0.047</CHANGE>
  </CURRENCY>
</CURRENCIES>