<CURRENCIES>
  <LAST_UPDATE>2023-12-28</LAST_UPDATE>
  <CURRENCY>
    <NAME>Dollar</NAME>
    <UNIT>1</UNIT>
    <CURRENCYCODE>USD</CURRENCYCODE>
    <COUNTRY>USA</COUNTRY>
    <RATE>3.6190</RATE>
    <CHANGE>-0.138%</CHANGE>
  </CURRENCY>
  <CURRENCY>
    <NAME>Pound</NAME>
    <UNIT>1</UNIT>
    <CURRENCYCODE>GBP</CURRENCYCODE>
    <COUNTRY>Great Britain</COUNTRY>
    <RATE>4.6198</RATE>
    <CHANGE>0.143%</CHANGE>
  </CURRENCY>
  <CURRENCY>
    <NAME>Yen</NAME>
    <UNIT>100</UNIT>
    <CURRENCYCODE>JPY</CURRENCYCODE>
    <COUNTRY>Japan</COUNTRY>
    <RATE>2.5692</RATE>
    <CHANGE>1.086%</CHANGE>
  </CURRENCY>
  <CURRENCY>
    <NAME>Euro</NAME>
    <UNIT>1</UNIT>
    <CURRENCYCODE>EUR</CURRENCYCODE>
    <COUNTRY>EMU</COUNTRY>
    <RATE>4.0222</RATE>
    <CHANGE>0.389%</CHANGE>
  </CURRENCY>
  <CURRENCY>
    <NAME>Dollar</NAME>
    <UNIT>1</UNIT>
    <CURRENCYCODE>AUD</CURRENCYCODE>
    <COUNTRY>Australia</COUNTRY>
    <RATE>2.4760</RATE>
    <CHANGE>-0.105%</CHANGE>
  </CURRENCY>
  <CURRENCY>
    <NAME>Dollar</NAME>
    <UNIT>1</UNIT>
    <CURRENCYCODE>CAD</CURRENCYCODE>
    <COUNTRY>Canada</COUNTRY>
    <RATE>2.7370</RATE>
    <CHANGE>-0.299%</CHANGE>
  </CURRENCY>
  <CURRENCY>
    <NAME>krone</NAME>
    <UNIT>1</UNIT>
    <CURRENCYCODE>DKK</CURRENCYCODE>
    <COUNTRY>Denmark</COUNTRY>
    <RATE>0.5396</RATE>
    <CHANGE>0.409%</CHANGE>
  </CURRENCY>
  <CURRENCY>
    <NAME>Krone</NAME>
    <UNIT>1</UNIT>
    <CURRENCYCODE>NOK</CURRENCYCODE>
    <COUNTRY>Norway</COUNTRY>
    <RATE>0.3572</RATE>
    <CHANGE>0.028%</CHANGE>
  </CURRENCY>
  <CURRENCY>
    <NAME>Rand</NAME>
    <UNIT>1</UNIT>
    <CURRENCYCODE>ZAR</CURRENCYCODE>
    <COUNTRY>South Africa</COUNTRY>
    <RATE>0.1953</RATE>
    <CHANGE>-0.459%</CHANGE>
  </CURRENCY>
  <CURRENCY>
    <NAME>Krona</NAME>
    <UNIT>1</UNIT>
    <CURRENCYCODE>SEK</CURRENCYCODE>
    <COUNTRY>Sweden</COUNTRY>
    <RATE>0.3644</RATE>
    <CHANGE>0.441%</CHANGE>
  </CURRENCY>
  <CURRENCY>
    <NAME>Franc</NAME>
    <UNIT>1</UNIT>
    <CURRENCYCODE>CHF</CURRENCYCODE>
    <COUNTRY>Switzerland</COUNTRY>
    <RATE>4.3232</RATE>
    <CHANGE>1.763%</CHANGE>
  </CURRENCY>
  <CURRENCY>
    <NAME>Dinar</NAME>
    <UNIT>1</UNIT>
    <CURRENCYCODE>JOD</CURRENCYCODE>
    <COUNTRY>Jordan</COUNTRY>
    <RATE>5.1021</RATE>
    <CHANGE>-0.033%</CHANGE>
  </CURRENCY>
  <CURRENCY>
    <NAME>Pound</NAME>
    <UNIT>10</UNIT>
    <CURRENCYCODE>LBP</CURRENCYCODE>
    <COUNTRY>Lebanon</COUNTRY>
    <RATE>0.0024</RATE>
    <CHANGE>0%</CHANGE>
  </CURRENCY>
  <CURRENCY>
    <NAME>Pound</NAME>
    <UNIT>1</UNIT>
    <CURRENCYCODE>EGP</CURRENCYCODE>
    <COUNTRY>Egypt</COUNTRY>
    <RATE>0.1169</RATE>
    <CHANGE>-0.341%</CHANGE>
  </CURRENCY>
</CURRENCIES>