<?xml version="1.0" encoding="utf-8" standalone="yes"?>
<CURRENCIES>
  <LAST_UPDATE>2018-11-14</LAST_UPDATE>
  <CURRENCY>
    <NAME>Dollar</NAME>
    <UNIT>1</UNIT>
    <CURRENCYCODE>USD</CURRENCYCODE>
    <COUNTRY>USA</COUNTRY>
    <RATE>3.698</RATE>
    <CHANGE>0.244</CHANGE>
  </CURRENCY>
  <CURRENCY>
    <NAME>Pound</NAME>
    <UNIT>1</UNIT>
    <CURRENCYCODE>GBP</CURRENCYCODE>
    <COUNTRY>Great Britain</COUNTRY>
    <RATE>4.7851</RATE>
    <CHANGE>0.397</CHANGE>
  </CURRENCY>
  <CURRENCY>
    <NAME>Yen</NAME>
    <UNIT>100</UNIT>
    <CURRENCYCODE>JPY</CURRENCYCODE>
    <COUNTRY>Japan</COUNTRY>
    <RATE>3.2473</RATE>
    <CHANGE>0.365</CHANGE>
  </CURRENCY>
  <CURRENCY>
    <NAME>Euro</NAME>
    <UNIT>1</UNIT>
    <CURRENCYCODE>EUR</CURRENCYCODE>
    <COUNTRY>EMU</COUNTRY>
    <RATE>4.1694</RATE>
    <CHANGE>0.455</CHANGE>
  </CURRENCY>
  <CURRENCY>
    <NAME>Dollar</NAME>
    <UNIT>1</UNIT>
    <CURRENCYCODE>AUD</CURRENCYCODE>
    <COUNTRY>Australia</COUNTRY>
    <RATE>2.6636</RATE>
    <CHANGE>0.301</CHANGE>
  </CURRENCY>
  <CURRENCY>
    <NAME>Dollar</NAME>
    <UNIT>1</UNIT>
    <CURRENCYCODE>CAD</CURRENCYCODE>
    <COUNTRY>Canada</COUNTRY>
    <RATE>2.7945</RATE>
    <CHANGE>0.273</CHANGE>
  </CURRENCY>
  <CURRENCY>
    <NAME>krone</NAME>
    <UNIT>1</UNIT>
    <CURRENCYCODE>DKK</CURRENCYCODE>
    <COUNTRY>Denmark</COUNTRY>
    <RATE>0.5588</RATE>
    <CHANGE>0.467</CHANGE>
  </CURRENCY>
  <CURRENCY>
    <NAME>Krone</NAME>
    <UNIT>1</UNIT>
    <CURRENCYCODE>NOK</CURRENCYCODE>
    <COUNTRY>Norway</COUNTRY>
    <RATE>0.4342</RATE>
    <CHANGE>0</CHANGE>
  </CURRENCY>
  <CURRENCY>
    <NAME>Rand</NAME>
    <UNIT>1</UNIT>
    <CURRENCYCODE>ZAR</CURRENCYCODE>
    <COUNTRY>South Africa</COUNTRY>
    <RATE>0.2568</RATE>
    <CHANGE>0.548</CHANGE>
  </CURRENCY>
  <CURRENCY>
    <NAME>Krona</NAME>
    <UNIT>1</UNIT>
    <CURRENCYCODE>SEK</CURRENCYCODE>
    <COUNTRY>Sweden</COUNTRY>
    <RATE>0.4059</RATE>
    <CHANGE>0.049</CHANGE>
  </CURRENCY>
  <CURRENCY>
    <NAME>Franc</NAME>
    <UNIT>1</UNIT>
    <CURRENCYCODE>CHF</CURRENCYCODE>
    <COUNTRY>Switzerland</COUNTRY>
    <RATE>3.6624</RATE>
    <CHANGE>0.285</CHANGE>
  </CURRENCY>
  <CURRENCY>
    <NAME>Dinar</NAME>
    <UNIT>1</UNIT>
    <CURRENCYCODE>JOD</CURRENCYCODE>
    <COUNTRY>Jordan</COUNTRY>
    <RATE>5.2120</RATE>
    <CHANGE>0.233</CHANGE>
  </CURRENCY>
  <CURRENCY>
    <NAME>Pound</NAME>
    <UNIT>10</UNIT>
    <CURRENCYCODE>LBP</CURRENCYCODE>
    <COUNTRY>Lebanon</COUNTRY>
    <RATE>0.0244</RATE>
    <CHANGE>0</CHANGE>
  </CURRENCY>
  <CURRENCY>
    <NAME>Pound</NAME>
    <UNIT>1</UNIT>
    <CURRENCYCODE>EGP</CURRENCYCODE>
    <COUNTRY>Egypt</COUNTRY>
    <RATE>0.2061</RATE>
    <CHANGE>0.341</CHANGE>
  </CURRENCY>
</CURRENCIES>