<?xml version="1.0" encoding="utf-8" standalone="yes"?>
<CURRENCIES>
  <LAST_UPDATE>2017-12-01</LAST_UPDATE>
  <CURRENCY>
    <NAME>Dollar</NAME>
    <UNIT>1</UNIT>
    <CURRENCYCODE>USD</CURRENCYCODE>
    <COUNTRY>USA</COUNTRY>
    <RATE>3.488</RATE>
    <CHANGE>-0.314</CHANGE>
  </CURRENCY>
  <CURRENCY>
    <NAME>Pound</NAME>
    <UNIT>1</UNIT>
    <CURRENCYCODE>GBP</CURRENCYCODE>
    <COUNTRY>Great Britain</COUNTRY>
    <RATE>4.7061</RATE>
    <CHANGE>0.045</CHANGE>
  </CURRENCY>
  <CURRENCY>
    <NAME>Yen</NAME>
    <UNIT>100</UNIT>
    <CURRENCYCODE>JPY</CURRENCYCODE>
    <COUNTRY>Japan</COUNTRY>
    <RATE>3.1026</RATE>
    <CHANGE>-0.395</CHANGE>
  </CURRENCY>
  <CURRENCY>
    <NAME>Euro</NAME>
    <UNIT>1</UNIT>
    <CURRENCYCODE>EUR</CURRENCYCODE>
    <COUNTRY>EMU</COUNTRY>
    <RATE>4.1521</RATE>
    <CHANGE>0.222</CHANGE>
  </CURRENCY>
  <CURRENCY>
    <NAME>Dollar</NAME>
    <UNIT>1</UNIT>
    <CURRENCYCODE>AUD</CURRENCYCODE>
    <COUNTRY>Australia</COUNTRY>
    <RATE>2.6462</RATE>
    <CHANGE>-0.019</CHANGE>
  </CURRENCY>
  <CURRENCY>
    <NAME>Dollar</NAME>
    <UNIT>1</UNIT>
    <CURRENCYCODE>CAD</CURRENCYCODE>
    <COUNTRY>Canada</COUNTRY>
    <RATE>2.7116</RATE>
    <CHANGE>-0.092</CHANGE>
  </CURRENCY>
  <CURRENCY>
    <NAME>krone</NAME>
    <UNIT>1</UNIT>
    <CURRENCYCODE>DKK</CURRENCYCODE>
    <COUNTRY>Denmark</COUNTRY>
    <RATE>0.5579</RATE>
    <CHANGE>0.216</CHANGE>
  </CURRENCY>
  <CURRENCY>
    <NAME>Krone</NAME>
    <UNIT>1</UNIT>
    <CURRENCYCODE>NOK</CURRENCYCODE>
    <COUNTRY>Norway</COUNTRY>
    <RATE>0.4207</RATE>
    <CHANGE>-0.308</CHANGE>
  </CURRENCY>
  <CURRENCY>
    <NAME>Rand</NAME>
    <UNIT>1</UNIT>
    <CURRENCYCODE>ZAR</CURRENCYCODE>
    <COUNTRY>South Africa</COUNTRY>
    <RATE>0.2542</RATE>
    <CHANGE>-1.128</CHANGE>
  </CURRENCY>
  <CURRENCY>
    <NAME>Krona</NAME>
    <UNIT>1</UNIT>
    <CURRENCYCODE>SEK</CURRENCYCODE>
    <COUNTRY>Sweden</COUNTRY>
    <RATE>0.4176</RATE>
    <CHANGE>-0.024</CHANGE>
  </CURRENCY>
  <CURRENCY>
    <NAME>Franc</NAME>
    <UNIT>1</UNIT>
    <CURRENCYCODE>CHF</CURRENCYCODE>
    <COUNTRY>Switzerland</COUNTRY>
    <RATE>3.5477</RATE>
    <CHANGE>-0.037</CHANGE>
  </CURRENCY>
  <CURRENCY>
    <NAME>Dinar</NAME>
    <UNIT>1</UNIT>
    <CURRENCYCODE>JOD</CURRENCYCODE>
    <COUNTRY>Jordan</COUNTRY>
    <RATE>4.9163</RATE>
    <CHANGE>-0.278</CHANGE>
  </CURRENCY>
  <CURRENCY>
    <NAME>Pound</NAME>
    <UNIT>10</UNIT>
    <CURRENCYCODE>LBP</CURRENCYCODE>
    <COUNTRY>Lebanon</COUNTRY>
    <RATE>0.0230</RATE>
    <CHANGE>-0.433</CHANGE>
  </CURRENCY>
  <CURRENCY>
    <NAME>Pound</NAME>
    <UNIT>1</UNIT>
    <CURRENCYCODE>EGP</CURRENCYCODE>
    <COUNTRY>Egypt</COUNTRY>
    <RATE>0.1973</RATE>
    <CHANGE>-0.303</CHANGE>
  </CURRENCY>
</CURRENCIES>